Workbook
Name SlicerCache_Table_2_Col_4: #N/A
Name SlicerCache_Table_2_Col_5: #N/A
Name SlicerCache_Table_2_Col_6: #N/A
Name SlicerCache_Table_2_Col_8: #N/A

Sheet Dataset
A1: Row ID | B1: Order Priority | C1: Discount | D1: Unit Price | E1: Customer ID | F1: Customer Name | G1: Customer Segment | H1: Product Category | I1: Product Sub-Category | J1: Product Name | K1: City | L1: Order Weekday | M1: Weekday helper | N1: Profit | O1: Quantity ordered new | P1: Sales | Q1: Order ID | R1: Order returned | S1: Order Date
A2: 20847 | B2: High | C2: 0.01 | D2: 2.84 | E2: 3 | F2: Bonnie Potter | G2: Corporate | H2: Office Supplies | I2: Pens & Art Supplies | J2: SANFORD Liquid Accent™ Tank-Style Highlighters | K2: Warsaw | L2: Wednesday | M2: =VLOOKUP(L2,$U$2:$V$8,2,0) -> 3 | N2: 4.56 | O2: 4 | P2: 13.01 | Q2: 88522 | R2: =ISNUMBER(MATCH(Q2,'Returned order'!A:A,0)) -> FALSE | S2: 42011 | U2: Monday | V2: 1
A3: 20228 | B3: Not Specified | C3: 0.02 | D3: 500.98 | E3: 5 | F3: Ronnie Proctor | G3: Home Office | H3: Furniture | I3: Chairs & Chairmats | J3: Global Troy™ Executive Leather Low-Back Tilter | K3: Warsaw | L3: Saturday | M3: =VLOOKUP(L3,$U$2:$V$8,2,0) -> 6 | N3: 4390.3665 | O3: 12 | P3: 6362.85 | Q3: 90193 | R3: =ISNUMBER(MATCH(Q3,'Returned order'!A:A,0)) -> FALSE | S3: 42168 | U3: Tuesday | V3: 2
A4: 21776 | B4: Critical | C4: 0.06 | D4: 9.48 | E4: 11 | F4: Marcus Dunlap | G4: Home Office | H4: Furniture | I4: Office Furnishings | J4: DAX Two-Tone Rosewood/Black Document Frame, Desktop, 5 x 7 | K4: Lodz | L4: Sunday | M4: =VLOOKUP(L4,$U$2:$V$8,2,0) -> 7 | N4: -53.8096 | O4: 22 | P4: 211.15 | Q4: 90192 | R4: =ISNUMBER(MATCH(Q4,'Returned order'!A:A,0)) -> FALSE | S4: 42050 | U4: Wednesday | V4: 3
A5: 24844 | B5: Medium | C5: 0.09 | D5: 78.69 | E5: 14 | F5: Gwendolyn F Tyson | G5: Small Business | H5: Furniture | I5: Office Furnishings | J5: Howard Miller 12-3/4 Diameter Accuwave DS ™ Wall Clock | K5: Krakow | L5: Tuesday | M5: =VLOOKUP(L5,$U$2:$V$8,2,0) -> 2 | N5: 803.4705 | O5: 16 | P5: 1164.45 | Q5: 86838 | R5: =ISNUMBER(MATCH(Q5,'Returned order'!A:A,0)) -> FALSE | S5: 42136 | U5: Thursday | V5: 4
A6: 24846 | B6: Medium | C6: 0.08 | D6: 3.28 | E6: 14 | F6: Gwendolyn F Tyson | G6: Small Business | H6: Office Supplies | I6: Pens & Art Supplies | J6: Newell 321 | K6: Krakow | L6: Tuesday | M6: =VLOOKUP(L6,$U$2:$V$8,2,0) -> 2 | N6: -24.03 | O6: 7 | P6: 22.23 | Q6: 86838 | R6: =ISNUMBER(MATCH(Q6,'Returned order'!A:A,0)) -> FALSE | S6: 42136 | U6: Friday | V6: 5
A7: 24847 | B7: Medium | C7: 0.05 | D7: 3.28 | E7: 14 | F7: Gwendolyn F Tyson | G7: Small Business | H7: Office Supplies | I7: Pens & Art Supplies | J7: Newell 351 | K7: Krakow | L7: Tuesday | M7: =VLOOKUP(L7,$U$2:$V$8,2,0) -> 2 | N7: -37.03 | O7: 4 | P7: 13.99 | Q7: 86838 | R7: =ISNUMBER(MATCH(Q7,'Returned order'!A:A,0)) -> FALSE | S7: 42136 | U7: Saturday | V7: 6
A8: 24848 | B8: Medium | C8: 0.05 | D8: 3.58 | E8: 14 | F8: Gwendolyn F Tyson | G8: Small Business | H8: Office Supplies | I8: Rubber Bands | J8: OIC Colored Binder Clips, Assorted Sizes | K8: Krakow | L8: Tuesday | M8: =VLOOKUP(L8,$U$2:$V$8,2,0) -> 2 | N8: -0.71 | O8: 4 | P8: 14.26 | Q8: 86838 | R8: =ISNUMBER(MATCH(Q8,'Returned order'!A:A,0)) -> FALSE | S8: 42136 | U8: Sunday | V8: 7
A9: 18181 | B9: Critical | C9: 0 | D9: 4.42 | E9: 15 | F9: Timothy Reese | G9: Small Business | H9: Office Supplies | I9: Envelopes | J9: Grip Seal Envelopes | K9: Lodz | L9: Wednesday | M9: =VLOOKUP(L9,$U$2:$V$8,2,0) -> 3 | N9: -59.82 | O9: 7 | P9: 33.47 | Q9: 86837 | R9: =ISNUMBER(MATCH(Q9,'Returned order'!A:A,0)) -> FALSE | S9: 42102
A10: 20925 | B10: Medium | C10: 0.01 | D10: 35.94 | E10: 15 | F10: Timothy Reese | G10: Small Business | H10: Office Supplies | I10: Envelopes | J10: Tyvek ® Top-Opening Peel & Seel ® Envelopes, Gray | K10: Lodz | L10: Thursday | M10: =VLOOKUP(L10,$U$2:$V$8,2,0) -> 4 | N10: 261.8757 | O10: 10 | P10: 379.53 | Q10: 86839 | R10: =ISNUMBER(MATCH(Q10,'Returned order'!A:A,0)) -> FALSE | S10: 42152
A11: 26267 | B11: High | C11: 0.04 | D11: 2.98 | E11: 16 | F11: Sarah Ramsey | G11: Small Business | H11: Office Supplies | I11: Rubber Bands | J11: Staples Gold Paper Clips | K11: Lodz | L11: Thursday | M11: =VLOOKUP(L11,$U$2:$V$8,2,0) -> 4 | N11: 2.63 | O11: 6 | P11: 18.8 | Q11: 86836 | R11: =ISNUMBER(MATCH(Q11,'Returned order'!A:A,0)) -> FALSE | S11: 42047
A12: 26268 | B12: High | C12: 0.05 | D12: 115.99 | E12: 16 | F12: Sarah Ramsey | G12: Small Business | H12: Technology | I12: Telephones and Communication | J12: StarTAC 7797 | K12: Lodz | L12: Thursday | M12: =VLOOKUP(L12,$U$2:$V$8,2,0) -> 4 | N12: 652.7331 | O12: 10 | P12: 945.99 | Q12: 86836 | R12: =ISNUMBER(MATCH(Q12,'Returned order'!A:A,0)) -> FALSE | S12: 42047
A13: 23890 | B13: High | C13: 0.05 | D13: 26.48 | E13: 18 | F13: Laurie Hanna | G13: Small Business | H13: Furniture | I13: Office Furnishings | J13: DAX Natural Wood-Tone Poster Frame | K13: Warsaw | L13: Friday | M13: =VLOOKUP(L13,$U$2:$V$8,2,0) -> 5 | N13: 314.4813 | O13: 17 | P13: 455.77 | Q13: 90031 | R13: =ISNUMBER(MATCH(Q13,'Returned order'!A:A,0)) -> FALSE | S13: 42139
A14: 24063 | B14: Not Specified | C14: 0.07 | D14: 12.99 | E14: 19 | F14: Jim Rodgers | G14: Small Business | H14: Technology | I14: Office Machines | J14: Hewlett Packard 6S Scientific Calculator | K14: Warsaw | L14: Thursday | M14: =VLOOKUP(L14,$U$2:$V$8,2,0) -> 4 | N14: -114.6399 | O14: 18 | P14: 231.79 | Q14: 90032 | R14: =ISNUMBER(MATCH(Q14,'Returned order'!A:A,0)) -> FALSE | S14: 42145
A15: 5890 | B15: High | C15: 0.05 | D15: 26.48 | E15: 21 | F15: Tony Wilkins Winters | G15: Small Business | H15: Furniture | I15: Office Furnishings | J15: DAX Natural Wood-Tone Poster Frame | K15: Lodz | L15: Friday | M15: =VLOOKUP(L15,$U$2:$V$8,2,0) -> 5 | N15: 384.38 | O15: 70 | P15: 1876.69 | Q15: 41793 | R15: =ISNUMBER(MATCH(Q15,'Returned order'!A:A,0)) -> FALSE | S15: 42139
A16: 6062 | B16: Not Specified | C16: 0.08 | D16: 5 | E16: 21 | F16: Tony Wilkins Winters | G16: Small Business | H16: Office Supplies | I16: Rubber Bands | J16: Advantus Plastic Paper Clips | K16: Lodz | L16: Thursday | M16: =VLOOKUP(L16,$U$2:$V$8,2,0) -> 4 | N16: -17.49 | O16: 58 | P16: 293.06 | Q16: 42949 | R16: =ISNUMBER(MATCH(Q16,'Returned order'!A:A,0)) -> FALSE | S16: 42145
A17: 6063 | B17: Not Specified | C17: 0.07 | D17: 12.99 | E17: 21 | F17: Tony Wilkins Winters | G17: Small Business | H17: Technology | I17: Office Machines | J17: Hewlett Packard 6S Scientific Calculator | K17: Lodz | L17: Thursday | M17: =VLOOKUP(L17,$U$2:$V$8,2,0) -> 4 | N17: -114.6399 | O17: 71 | P17: 914.29 | Q17: 42949 | R17: =ISNUMBER(MATCH(Q17,'Returned order'!A:A,0)) -> FALSE | S17: 42145
A18: 20631 | B18: High | C18: 0.06 | D18: 55.48 | E18: 24 | F18: Edna Thomas | G18: Corporate | H18: Office Supplies | I18: Paper | J18: Xerox 194 | K18: Warsaw | L18: Wednesday | M18: =VLOOKUP(L18,$U$2:$V$8,2,0) -> 3 | N18: -28.2968 | O18: 1 | P18: 67.49 | Q18: 87651 | R18: =ISNUMBER(MATCH(Q18,'Returned order'!A:A,0)) -> FALSE | S18: 42032
A19: 20632 | B19: High | C19: 0.02 | D19: 1.68 | E19: 24 | F19: Edna Thomas | G19: Corporate | H19: Office Supplies | I19: Pens & Art Supplies | J19: Newell 323 | K19: Warsaw | L19: Wednesday | M19: =VLOOKUP(L19,$U$2:$V$8,2,0) -> 3 | N19: -5.3072 | O19: 1 | P19: 2.25 | Q19: 87651 | R19: =ISNUMBER(MATCH(Q19,'Returned order'!A:A,0)) -> FALSE | S19: 42032
A20: 23967 | B20: Not Specified | C20: 0.04 | D20: 4.14 | E20: 27 | F20: Guy Gallagher | G20: Corporate | H20: Furniture | I20: Office Furnishings | J20: Eldon Image Series Black Desk Accessories | K20: Warsaw | L20: Saturday | M20: =VLOOKUP(L20,$U$2:$V$8,2,0) -> 6 | N20: 8.894 | O20: 12 | P20: 54.78 | Q20: 87652 | R20: =ISNUMBER(MATCH(Q20,'Returned order'!A:A,0)) -> FALSE | S20: 42126
... A27: 25933 | B27: High | C27: 0 | D27: 99.99 | E27: 43 | F27: Theodore Moran | G27: Consumer | H27: Technology | I27: Office Machines | J27: AT&T 2230 Dual Handset Phone With Caller ID/Call Waiting | K27: Warsaw | L27: Sunday | M27: =VLOOKUP(L27,$U$2:$V$8,2,0) -> 7 | N27: 25.91382 | O27: 6 | P27: 647.07 | Q27: 91454 | R27: =ISNUMBER(MATCH(Q27,'Returned order'!A:A,0)) -> FALSE | S27: 42134
A28: 18551 | B28: Not Specified | C28: 0 | D28: 115.99 | E28: 52 | F28: Lorraine Kelly | G28: Corporate | H28: Technology | I28: Telephones and Communication | J28: 6160 | K28: Warsaw | L28: Tuesday | M28: =VLOOKUP(L28,$U$2:$V$8,2,0) -> 2 | N28: 162.666 | O28: 6 | P28: 627.04 | Q28: 88426 | R28: =ISNUMBER(MATCH(Q28,'Returned order'!A:A,0)) -> FALSE | S28: 42073
A29: 22117 | B29: Critical | C29: 0.07 | D29: 3502.14 | E29: 53 | F29: Sidney Russell Austin | G29: Corporate | H29: Technology | I29: Office Machines | J29: Okidata Pacemark 4410N Wide Format Dot Matrix Printer | K29: Warsaw | L29: Wednesday | M29: =VLOOKUP(L29,$U$2:$V$8,2,0) -> 3 | N29: -6923.5992 | O29: 1 | P29: 3267.55 | Q29: 88425 | R29: =ISNUMBER(MATCH(Q29,'Returned order'!A:A,0)) -> FALSE | S29: 42032
A30: 18552 | B30: Not Specified | C30: 0.02 | D30: 5.98 | E30: 53 | F30: Sidney Russell Austin | G30: Corporate | H30: Office Supplies | I30: Paper | J30: Xerox 1903 | K30: Warsaw | L30: Tuesday | M30: =VLOOKUP(L30,$U$2:$V$8,2,0) -> 2 | N30: -67.49 | O30: 17 | P30: 110.19 | Q30: 88426 | R30: =ISNUMBER(MATCH(Q30,'Returned order'!A:A,0)) -> FALSE | S30: 42073
A31: 20697 | B31: Medium | C31: 0.06 | D31: 3.8 | E31: 56 | F31: Randall Montgomery | G31: Consumer | H31: Office Supplies | I31: Binders and Binder Accessories | J31: Durable Pressboard Binders | K31: Lodz | L31: Monday | M31: =VLOOKUP(L31,$U$2:$V$8,2,0) -> 1 | N31: 19.6282 | O31: 20 | P31: 73.55 | Q31: 88075 | R31: =ISNUMBER(MATCH(Q31,'Returned order'!A:A,0)) -> FALSE | S31: 42114
A32: 20698 | B32: Medium | C32: 0.06 | D32: 1.76 | E32: 56 | F32: Randall Montgomery | G32: Consumer | H32: Office Supplies | I32: Pens & Art Supplies | J32: Newell 310 | K32: Lodz | L32: Monday | M32: =VLOOKUP(L32,$U$2:$V$8,2,0) -> 1 | N32: -1.6524 | O32: 17 | P32: 29.57 | Q32: 88075 | R32: =ISNUMBER(MATCH(Q32,'Returned order'!A:A,0)) -> FALSE | S32: 42114
A33: 22890 | B33: High | C33: 0.02 | D33: 5.98 | E33: 62 | F33: Pam Gilbert | G33: Corporate | H33: Office Supplies | I33: Paper | J33: Xerox 193 | K33: Krakow | L33: Saturday | M33: =VLOOKUP(L33,$U$2:$V$8,2,0) -> 6 | N33: 2.14 | O33: 3 | P33: 22.85 | Q33: 87407 | R33: =ISNUMBER(MATCH(Q33,'Returned order'!A:A,0)) -> FALSE | S33: 42133
A34: 25354 | B34: High | C34: 0.04 | D34: 29.14 | E34: 62 | F34: Pam Gilbert | G34: Corporate | H34: Office Supplies | I34: Paper | J34: Snap-A-Way® Black Print Carbonless Speed Message, No Reply Area, Duplicate | K34: Krakow | L34: Friday | M34: =VLOOKUP(L34,$U$2:$V$8,2,0) -> 5 | N34: 349.4091 | O34: 17 | P34: 506.39 | Q34: 87408 | R34: =ISNUMBER(MATCH(Q34,'Returned order'!A:A,0)) -> FALSE | S34: 42167
A35: 21017 | B35: Not Specified | C35: 0 | D35: 3.69 | E35: 64 | F35: Lynn Morrow | G35: Small Business | H35: Office Supplies | I35: Labels | J35: Avery 501 | K35: Wroclaw | L35: Monday | M35: =VLOOKUP(L35,$U$2:$V$8,2,0) -> 1 | N35: -37.5291 | O35: 1 | P35: 4 | Q35: 87406 | R35: =ISNUMBER(MATCH(Q35,'Returned order'!A:A,0)) -> FALSE | S35: 42065
A36: 21019 | B36: Not Specified | C36: 0.02 | D36: 175.99 | E36: 64 | F36: Lynn Morrow | G36: Small Business | H36: Technology | I36: Telephones and Communication | J36: 5165 | K36: Wroclaw | L36: Monday | M36: =VLOOKUP(L36,$U$2:$V$8,2,0) -> 1 | N36: 101.49 | O36: 4 | P36: 589.8 | Q36: 87406 | R36: =ISNUMBER(MATCH(Q36,'Returned order'!A:A,0)) -> FALSE | S36: 42065
A37: 23274 | B37: Low | C37: 0.05 | D37: 155.06 | E37: 67 | F37: Ellen McCormick | G37: Corporate | H37: Office Supplies | I37: Storage & Organization | J37: Dual Level, Single-Width Filing Carts | K37: Warsaw | L37: Friday | M37: =VLOOKUP(L37,$U$2:$V$8,2,0) -> 5 | N37: 845.664 | O37: 8 | P37: 1225.6 | Q37: 87946 | R37: =ISNUMBER(MATCH(Q37,'Returned order'!A:A,0)) -> FALSE | S37: 42006
A38: 5272 | B38: Low | C38: 0 | D38: 291.73 | E38: 68 | F38: Scott Bunn | G38: Corporate | H38: Furniture | I38: Chairs & Chairmats | J38: Hon 4070 Series Pagoda™ Armless Upholstered Stacking Chairs | K38: Lodz | L38: Friday | M38: =VLOOKUP(L38,$U$2:$V$8,2,0) -> 5 | N38: -308.928 | O38: 4 | P38: 1239.06 | Q38: 37537 | R38: =ISNUMBER(MATCH(Q38,'Returned order'!A:A,0)) -> FALSE | S38: 42006
A39: 5273 | B39: Low | C39: 0.07 | D39: 100.98 | E39: 68 | F39: Scott Bunn | G39: Corporate | H39: Furniture | I39: Chairs & Chairmats | J39: Hon Valutask™ Swivel Chairs | K39: Lodz | L39: Friday | M39: =VLOOKUP(L39,$U$2:$V$8,2,0) -> 5 | N39: -1679.76 | O39: 43 | P39: 4083.19 | Q39: 37537 | R39: =ISNUMBER(MATCH(Q39,'Returned order'!A:A,0)) -> FALSE | S39: 42006
A40: 5274 | B40: Low | C40: 0.05 | D40: 155.06 | E40: 68 | F40: Scott Bunn | G40: Corporate | H40: Office Supplies | I40: Storage & Organization | J40: Dual Level, Single-Width Filing Carts | K40: Lodz | L40: Friday | M40: =VLOOKUP(L40,$U$2:$V$8,2,0) -> 5 | N40: 575.396 | O40: 32 | P40: 4902.38 | Q40: 37537 | R40: =ISNUMBER(MATCH(Q40,'Returned order'!A:A,0)) -> FALSE | S40: 42006
A41: 7786 | B41: High | C41: 0.09 | D41: 122.99 | E41: 68 | F41: Scott Bunn | G41: Corporate | H41: Furniture | I41: Chairs & Chairmats | J41: Global High-Back Leather Tilter, Burgundy | K41: Lodz | L41: Monday | M41: =VLOOKUP(L41,$U$2:$V$8,2,0) -> 1 | N41: -2426.55 | O41: 49 | P41: 5718.85 | Q41: 55713 | R41: =ISNUMBER(MATCH(Q41,'Returned order'!A:A,0)) -> FALSE | S41: 42037
A42: 25786 | B42: High | C42: 0.09 | D42: 122.99 | E42: 70 | F42: Annette Boone | G42: Corporate | H42: Furniture | I42: Chairs & Chairmats | J42: Global High-Back Leather Tilter, Burgundy | K42: Lodz | L42: Monday | M42: =VLOOKUP(L42,$U$2:$V$8,2,0) -> 1 | N42: -2426.55 | O42: 12 | P42: 1400.53 | Q42: 87947 | R42: =ISNUMBER(MATCH(Q42,'Returned order'!A:A,0)) -> FALSE | S42: 42037
A43: 18281 | B43: High | C43: 0.04 | D43: 296.18 | E43: 83 | F43: Edgar Stone | G43: Corporate | H43: Furniture | I43: Tables | J43: Hon 94000 Series Round Tables | K43: Lodz | L43: Sunday | M43: =VLOOKUP(L43,$U$2:$V$8,2,0) -> 7 | N43: -715.77821 | O43: 6 | P43: 1821.89 | Q43: 87365 | R43: =ISNUMBER(MATCH(Q43,'Returned order'!A:A,0)) -> FALSE | S43: 42078
A44: 23639 | B44: Not Specified | C44: 0 | D44: 8.09 | E44: 84 | F44: Helen Stein | G44: Consumer | H44: Furniture | I44: Office Furnishings | J44: 6" Cubicle Wall Clock, Black | K44: Lodz | L44: Monday | M44: =VLOOKUP(L44,$U$2:$V$8,2,0) -> 1 | N44: -144.56 | O44: 11 | P44: 90.98 | Q44: 87364 | R44: =ISNUMBER(MATCH(Q44,'Returned order'!A:A,0)) -> FALSE | S44: 42037
A45: 23880 | B45: High | C45: 0.08 | D45: 896.99 | E45: 84 | F45: Helen Stein | G45: Corporate | H45: Office Supplies | I45: Binders and Binder Accessories | J45: GBC DocuBind TL300 Electric Binding System | K45: Lodz | L45: Monday | M45: =VLOOKUP(L45,$U$2:$V$8,2,0) -> 1 | N45: 7402.32 | O45: 13 | P45: 10728 | Q45: 87366 | R45: =ISNUMBER(MATCH(Q45,'Returned order'!A:A,0)) -> FALSE | S45: 42093
A46: 24663 | B46: Low | C46: 0.05 | D46: 161.55 | E46: 87 | F46: Norman Shields | G46: Corporate | H46: Office Supplies | I46: Storage & Organization | J46: Fellowes Super Stor/Drawer® Files | K46: Warsaw | L46: Wednesday | M46: =VLOOKUP(L46,$U$2:$V$8,2,0) -> 3 | N46: 1892.424 | O46: 19 | P46: 3127.69 | Q46: 90596 | R46: =ISNUMBER(MATCH(Q46,'Returned order'!A:A,0)) -> FALSE | S46: 42158
A47: 23841 | B47: High | C47: 0.09 | D47: 4.91 | E47: 87 | F47: Norman Shields | G47: Corporate | H47: Office Supplies | I47: Labels | J47: Avery 493 | K47: Warsaw | L47: Sunday | M47: =VLOOKUP(L47,$U$2:$V$8,2,0) -> 7 | N47: 28.8558 | O47: 9 | P47: 41.82 | Q47: 90597 | R47: =ISNUMBER(MATCH(Q47,'Returned order'!A:A,0)) -> FALSE | S47: 42085
A48: 23842 | B48: High | C48: 0.01 | D48: 296.18 | E48: 87 | F48: Norman Shields | G48: Corporate | H48: Furniture | I48: Tables | J48: Hon 94000 Series Round Tables | K48: Warsaw | L48: Sunday | M48: =VLOOKUP(L48,$U$2:$V$8,2,0) -> 7 | N48: 173.48 | O48: 9 | P48: 2875.72 | Q48: 90597 | R48: =ISNUMBER(MATCH(Q48,'Returned order'!A:A,0)) -> FALSE | S48: 42085
... A50: 19877 | B50: Medium | C50: 0.05 | D50: 5.18 | E50: 91 | F50: Wallace Werner | G50: Home Office | H50: Office Supplies | I50: Paper | J50: Array® Memo Cubes | K50: Warsaw | L50: Wednesday | M50: =VLOOKUP(L50,$U$2:$V$8,2,0) -> 3 | N50: 34.0104 | O50: 10 | P50: 53.54 | Q50: 87176 | R50: =ISNUMBER(MATCH(Q50,'Returned order'!A:A,0)) -> FALSE | S50: 42053
A51: 19611 | B51: Medium | C51: 0.06 | D51: 175.99 | E51: 91 | F51: Wallace Werner | G51: Corporate | H51: Technology | I51: Telephones and Communication | J51: 2180 | K51: Warsaw | L51: Wednesday | M51: =VLOOKUP(L51,$U$2:$V$8,2,0) -> 3 | N51: 2031.507 | O51: 23 | P51: 3363.53 | Q51: 87177 | R51: =ISNUMBER(MATCH(Q51,'Returned order'!A:A,0)) -> FALSE | S51: 42067
A52: 23069 | B52: High | C52: 0.07 | D52: 8.34 | E52: 92 | F52: Victoria Baker Hoover | G52: Home Office | H52: Office Supplies | I52: Paper | J52: REDIFORM Incoming/Outgoing Call Register, 11" X 8 1/2", 100 Messages | K52: Wroclaw | L52: Sunday | M52: =VLOOKUP(L52,$U$2:$V$8,2,0) -> 7 | N52: -190.68 | O52: 16 | P52: 132.08 | Q52: 87175 | R52: =ISNUMBER(MATCH(Q52,'Returned order'!A:A,0)) -> FALSE | S52: 42141
A53: 23070 | B53: High | C53: 0.09 | D53: 4.98 | E53: 92 | F53: Victoria Baker Hoover | G53: Home Office | H53: Office Supplies | I53: Paper | J53: Xerox 1897 | K53: Wroclaw | L53: Sunday | M53: =VLOOKUP(L53,$U$2:$V$8,2,0) -> 7 | N53: 325.398 | O53: 9 | P53: 45.34 | Q53: 87175 | R53: =ISNUMBER(MATCH(Q53,'Returned order'!A:A,0)) -> FALSE | S53: 42141
A54: 23203 | B54: Medium | C54: 0.04 | D54: 12.98 | E54: 92 | F54: Victoria Baker Hoover | G54: Corporate | H54: Office Supplies | I54: Scissors, Rulers and Trimmers | J54: Acme® 8" Straight Scissors | K54: Wroclaw | L54: Sunday | M54: =VLOOKUP(L54,$U$2:$V$8,2,0) -> 7 | N54: 22.818 | O54: 16 | P54: 216.04 | Q54: 87178 | R54: =ISNUMBER(MATCH(Q54,'Returned order'!A:A,0)) -> FALSE | S54: 42162
A55: 6243 | B55: Not Specified | C55: 0.04 | D55: 160.98 | E55: 94 | F55: Eddie House Mueller | G55: Home Office | H55: Furniture | I55: Chairs & Chairmats | J55: Office Star - Mid Back Dual function Ergonomic High Back Chair with 2-Way Adjustable Arms | K55: Krakow | L55: Sunday | M55: =VLOOKUP(L55,$U$2:$V$8,2,0) -> 7 | N55: 116.1 | O55: 37 | P55: 6276.34 | Q55: 44231 | R55: =ISNUMBER(MATCH(Q55,'Returned order'!A:A,0)) -> FALSE | S55: 42127
A56: 6244 | B56: Not Specified | C56: 0.01 | D56: 17.98 | E56: 94 | F56: Eddie House Mueller | G56: Home Office | H56: Technology | I56: Computer Peripherals | J56: Belkin 107-key enhanced keyboard, USB/PS/2 interface | K56: Krakow | L56: Sunday | M56: =VLOOKUP(L56,$U$2:$V$8,2,0) -> 7 | N56: -87.96 | O56: 146 | P56: 2664.4 | Q56: 44231 | R56: =ISNUMBER(MATCH(Q56,'Returned order'!A:A,0)) -> FALSE | S56: 42127
A57: 24243 | B57: Not Specified | C57: 0.04 | D57: 160.98 | E57: 97 | F57: Max McKenna | G57: Home Office | H57: Furniture | I57: Chairs & Chairmats | J57: Office Star - Mid Back Dual function Ergonomic High Back Chair with 2-Way Adjustable Arms | K57: Krakow | L57: Sunday | M57: =VLOOKUP(L57,$U$2:$V$8,2,0) -> 7 | N57: 255.42 | O57: 9 | P57: 1526.68 | Q57: 87306 | R57: =ISNUMBER(MATCH(Q57,'Returned order'!A:A,0)) -> FALSE | S57: 42127
A58: 24245 | B58: Not Specified | C58: 0.06 | D58: 115.99 | E58: 97 | F58: Max McKenna | G58: Home Office | H58: Technology | I58: Telephones and Communication | J58: 5185 | K58: Krakow | L58: Sunday | M58: =VLOOKUP(L58,$U$2:$V$8,2,0) -> 7 | N58: 685.6146 | O58: 20 | P58: 1952.56 | Q58: 87306 | R58: =ISNUMBER(MATCH(Q58,'Returned order'!A:A,0)) -> FALSE | S58: 42127
A59: 18494 | B59: Medium | C59: 0.1 | D59: 19.98 | E59: 101 | F59: Claudia Boyle | G59: Consumer | H59: Technology | I59: Computer Peripherals | J59: Belkin 105-Key Black Keyboard | K59: Lodz | L59: Monday | M59: =VLOOKUP(L59,$U$2:$V$8,2,0) -> 1 | N59: -16.2 | O59: 16 | P59: 303.59 | Q59: 88205 | R59: =ISNUMBER(MATCH(Q59,'Returned order'!A:A,0)) -> FALSE | S59: 42177
A60: 6014 | B60: Medium | C60: 0.04 | D60: 300.98 | E60: 102 | F60: Caroline Johnston | G60: Consumer | H60: Furniture | I60: Bookcases | J60: Atlantic Metals Mobile 5-Shelf Bookcases, Custom Colors | K60: Lodz | L60: Monday | M60: =VLOOKUP(L60,$U$2:$V$8,2,0) -> 1 | N60: 2023.75 | O60: 31 | P60: 9459.94 | Q60: 42599 | R60: =ISNUMBER(MATCH(Q60,'Returned order'!A:A,0)) -> FALSE | S60: 42100
A61: 494 | B61: Medium | C61: 0.1 | D61: 19.98 | E61: 102 | F61: Caroline Johnston | G61: Consumer | H61: Technology | I61: Computer Peripherals | J61: Belkin 105-Key Black Keyboard | K61: Lodz | L61: Monday | M61: =VLOOKUP(L61,$U$2:$V$8,2,0) -> 1 | N61: -20.25 | O61: 65 | P61: 1233.32 | Q61: 3397 | R61: =ISNUMBER(MATCH(Q61,'Returned order'!A:A,0)) -> FALSE | S61: 42177
A62: 495 | B62: Medium | C62: 0.09 | D62: 2.88 | E62: 102 | F62: Caroline Johnston | G62: Consumer | H62: Office Supplies | I62: Binders and Binder Accessories | J62: Avery Durable Binders | K62: Lodz | L62: Monday | M62: =VLOOKUP(L62,$U$2:$V$8,2,0) -> 1 | N62: -3.381 | O62: 17 | P62: 47.31 | Q62: 3397 | R62: =ISNUMBER(MATCH(Q62,'Returned order'!A:A,0)) -> FALSE | S62: 42177
A63: 24014 | B63: Medium | C63: 0.04 | D63: 300.98 | E63: 107 | F63: Lois Hamilton | G63: Consumer | H63: Furniture | I63: Bookcases | J63: Atlantic Metals Mobile 5-Shelf Bookcases, Custom Colors | K63: Lodz | L63: Monday | M63: =VLOOKUP(L63,$U$2:$V$8,2,0) -> 1 | N63: 1684.4763 | O63: 8 | P63: 2441.27 | Q63: 88204 | R63: =ISNUMBER(MATCH(Q63,'Returned order'!A:A,0)) -> FALSE | S63: 42100
A64: 18495 | B64: Medium | C64: 0.09 | D64: 2.88 | E64: 109 | F64: Tom McFarland | G64: Consumer | H64: Office Supplies | I64: Binders and Binder Accessories | J64: Avery Durable Binders | K64: Lodz | L64: Monday | M64: =VLOOKUP(L64,$U$2:$V$8,2,0) -> 1 | N64: -2.7048 | O64: 4 | P64: 11.13 | Q64: 88205 | R64: =ISNUMBER(MATCH(Q64,'Returned order'!A:A,0)) -> FALSE | S64: 42177
A65: 19074 | B65: High | C65: 0.03 | D65: 4.26 | E65: 114 | F65: Ron Newton | G65: Home Office | H65: Office Supplies | I65: Pens & Art Supplies | J65: Dixon Prang® Watercolor Pencils, 10-Color Set with Brush | K65: Warsaw | L65: Saturday | M65: =VLOOKUP(L65,$U$2:$V$8,2,0) -> 6 | N65: 18.658 | O65: 7 | P65: 29.5 | Q65: 89583 | R65: =ISNUMBER(MATCH(Q65,'Returned order'!A:A,0)) -> FALSE | S65: 42007
A66: 19950 | B66: Medium | C66: 0.01 | D66: 4.91 | E66: 114 | F66: Ron Newton | G66: Home Office | H66: Office Supplies | I66: Labels | J66: Avery 493 | K66: Warsaw | L66: Saturday | M66: =VLOOKUP(L66,$U$2:$V$8,2,0) -> 6 | N66: 40.2477 | O66: 12 | P66: 58.33 | Q66: 89584 | R66: =ISNUMBER(MATCH(Q66,'Returned order'!A:A,0)) -> FALSE | S66: 42098
A67: 19951 | B67: Medium | C67: 0.09 | D67: 4 | E67: 114 | F67: Ron Newton | G67: Home Office | H67: Office Supplies | I67: Paper | J67: EcoTones® Memo Sheets | K67: Warsaw | L67: Saturday | M67: =VLOOKUP(L67,$U$2:$V$8,2,0) -> 6 | N67: 14.0898 | O67: 5 | P67: 20.42 | Q67: 89584 | R67: =ISNUMBER(MATCH(Q67,'Returned order'!A:A,0)) -> FALSE | S67: 42098
A68: 26241 | B68: Low | C68: 0.07 | D68: 2.12 | E68: 115 | F68: Dwight M Carr | G68: Home Office | H68: Technology | I68: Computer Peripherals | J68: Fuji Slim Jewel Case CD-R | K68: Warsaw | L68: Thursday | M68: =VLOOKUP(L68,$U$2:$V$8,2,0) -> 4 | N68: -55.84 | O68: 12 | P68: 26.07 | Q68: 89585 | R68: =ISNUMBER(MATCH(Q68,'Returned order'!A:A,0)) -> FALSE | S68: 42103
A69: 1074 | B69: High | C69: 0.03 | D69: 4.26 | E69: 117 | F69: Linda Weiss | G69: Home Office | H69: Office Supplies | I69: Pens & Art Supplies | J69: Dixon Prang® Watercolor Pencils, 10-Color Set with Brush | K69: Warsaw | L69: Saturday | M69: =VLOOKUP(L69,$U$2:$V$8,2,0) -> 6 | N69: 9.82 | O69: 29 | P69: 122.23 | Q69: 7909 | R69: =ISNUMBER(MATCH(Q69,'Returned order'!A:A,0)) -> FALSE | S69: 42007
A70: 1950 | B70: Medium | C70: 0.01 | D70: 4.91 | E70: 117 | F70: Linda Weiss | G70: Home Office | H70: Office Supplies | I70: Labels | J70: Avery 493 | K70: Warsaw | L70: Saturday | M70: =VLOOKUP(L70,$U$2:$V$8,2,0) -> 6 | N70: 112.06 | O70: 47 | P70: 228.46 | Q70: 13959 | R70: =ISNUMBER(MATCH(Q70,'Returned order'!A:A,0)) -> TRUE | S70: 42098
... A73: 20688 | B73: High | C73: 0.05 | D73: 6.3 | E73: 120 | F73: Helen H Murphy | G73: Corporate | H73: Office Supplies | I73: Labels | J73: Avery 51 | K73: Warsaw | L73: Monday | M73: =VLOOKUP(L73,$U$2:$V$8,2,0) -> 1 | N73: 41.2965 | O73: 10 | P73: 59.85 | Q73: 86520 | R73: =ISNUMBER(MATCH(Q73,'Returned order'!A:A,0)) -> FALSE | S73: 42016
A74: 20689 | B74: High | C74: 0.09 | D74: 205.99 | E74: 120 | F74: Helen H Murphy | G74: Corporate | H74: Technology | I74: Telephones and Communication | J74: 6185 | K74: Warsaw | L74: Monday | M74: =VLOOKUP(L74,$U$2:$V$8,2,0) -> 1 | N74: 1179.0237 | O74: 10 | P74: 1708.73 | Q74: 86520 | R74: =ISNUMBER(MATCH(Q74,'Returned order'!A:A,0)) -> FALSE | S74: 42016
A75: 19942 | B75: Critical | C75: 0.06 | D75: 8.57 | E75: 123 | F75: Shawn Stern | G75: Home Office | H75: Office Supplies | I75: Scissors, Rulers and Trimmers | J75: Acme® Office Executive Series Stainless Steel Trimmers | K75: Wroclaw | L75: Thursday | M75: =VLOOKUP(L75,$U$2:$V$8,2,0) -> 4 | N75: 105.678 | O75: 11 | P75: 94.97 | Q75: 90669 | R75: =ISNUMBER(MATCH(Q75,'Returned order'!A:A,0)) -> FALSE | S75: 42103
A76: 24319 | B76: Not Specified | C76: 0.02 | D76: 1.74 | E76: 129 | F76: Kara Allison | G76: Small Business | H76: Furniture | I76: Office Furnishings | J76: Eldon Regeneration Recycled Desk Accessories, Smoke | K76: Krakow | L76: Tuesday | M76: =VLOOKUP(L76,$U$2:$V$8,2,0) -> 2 | N76: -37.39 | O76: 5 | P76: 10.23 | Q76: 86693 | R76: =ISNUMBER(MATCH(Q76,'Returned order'!A:A,0)) -> FALSE | S76: 42031
A77: 18161 | B77: Not Specified | C77: 0.07 | D77: 15.74 | E77: 129 | F77: Kara Allison | G77: Small Business | H77: Office Supplies | I77: Envelopes | J77: #10-4 1/8" x 9 1/2" Premium Diagonal Seam Envelopes | K77: Krakow | L77: Monday | M77: =VLOOKUP(L77,$U$2:$V$8,2,0) -> 1 | N77: 149.8887 | O77: 14 | P77: 217.23 | Q77: 86694 | R77: =ISNUMBER(MATCH(Q77,'Returned order'!A:A,0)) -> FALSE | S77: 42149
A78: 25762 | B78: Critical | C78: 0.04 | D78: 18.97 | E78: 136 | F78: Dale Gillespie | G78: Small Business | H78: Office Supplies | I78: Paper | J78: Xerox 1939 | K78: Warsaw | L78: Saturday | M78: =VLOOKUP(L78,$U$2:$V$8,2,0) -> 6 | N78: 3.04 | O78: 5 | P78: 101.74 | Q78: 88534 | R78: =ISNUMBER(MATCH(Q78,'Returned order'!A:A,0)) -> FALSE | S78: 42140
A79: 25764 | B79: Critical | C79: 0.09 | D79: 10.98 | E79: 136 | F79: Dale Gillespie | G79: Small Business | H79: Office Supplies | I79: Scissors, Rulers and Trimmers | J79: Fiskars® Softgrip Scissors | K79: Warsaw | L79: Saturday | M79: =VLOOKUP(L79,$U$2:$V$8,2,0) -> 6 | N79: 2.706 | O79: 8 | P79: 84.52 | Q79: 88534 | R79: =ISNUMBER(MATCH(Q79,'Returned order'!A:A,0)) -> FALSE | S79: 42140
A80: 24803 | B80: Critical | C80: 0.03 | D80: 22.84 | E80: 142 | F80: Brooke Weeks Taylor | G80: Small Business | H80: Office Supplies | I80: Paper | J80: Xerox 1964 | K80: Lodz | L80: Tuesday | M80: =VLOOKUP(L80,$U$2:$V$8,2,0) -> 2 | N80: 91.956 | O80: 13 | P80: 312.59 | Q80: 91087 | R80: =ISNUMBER(MATCH(Q80,'Returned order'!A:A,0)) -> FALSE | S80: 42157
A81: 24805 | B81: Critical | C81: 0.05 | D81: 10.98 | E81: 144 | F81: Marguerite Moss | G81: Small Business | H81: Office Supplies | I81: Scissors, Rulers and Trimmers | J81: Fiskars® Softgrip Scissors | K81: Lodz | L81: Tuesday | M81: =VLOOKUP(L81,$U$2:$V$8,2,0) -> 2 | N81: -2.544 | O81: 6 | P81: 64.4 | Q81: 91087 | R81: =ISNUMBER(MATCH(Q81,'Returned order'!A:A,0)) -> FALSE | S81: 42157
A82: 24849 | B82: Medium | C82: 0.06 | D82: 7.04 | E82: 145 | F82: Rhonda Ivey | G82: Small Business | H82: Office Supplies | I82: Paper | J82: Wirebound Message Books, 2 7/8" x 5", 3 Forms per Page | K82: Lodz | L82: Thursday | M82: =VLOOKUP(L82,$U$2:$V$8,2,0) -> 4 | N82: 2.4852 | O82: 2 | P82: 14.65 | Q82: 91086 | R82: =ISNUMBER(MATCH(Q82,'Returned order'!A:A,0)) -> FALSE | S82: 42019
A83: 25582 | B83: Low | C83: 0.07 | D83: 154.13 | E83: 145 | F83: Rhonda Ivey | G83: Home Office | H83: Furniture | I83: Tables | J83: Laminate Occasional Tables | K83: Lodz | L83: Monday | M83: =VLOOKUP(L83,$U$2:$V$8,2,0) -> 1 | N83: -634.7341 | O83: 3 | P83: 453.62 | Q83: 91089 | R83: =ISNUMBER(MATCH(Q83,'Returned order'!A:A,0)) -> FALSE | S83: 42079
A84: 23365 | B84: Not Specified | C84: 0.01 | D84: 45.98 | E84: 146 | F84: Yvonne Fox | G84: Small Business | H84: Furniture | I84: Office Furnishings | J84: Tenex B1-RE Series Chair Mats for Low Pile Carpets | K84: Krakow | L84: Thursday | M84: =VLOOKUP(L84,$U$2:$V$8,2,0) -> 4 | N84: 133.5771 | O84: 4 | P84: 193.59 | Q84: 91088 | R84: =ISNUMBER(MATCH(Q84,'Returned order'!A:A,0)) -> FALSE | S84: 42075
A85: 22907 | B85: Medium | C85: 0.06 | D85: 180.98 | E85: 146 | F85: Yvonne Fox | G85: Corporate | H85: Furniture | I85: Chairs & Chairmats | J85: Global Ergonomic Managers Chair | K85: Krakow | L85: Thursday | M85: =VLOOKUP(L85,$U$2:$V$8,2,0) -> 4 | N85: 251.4084 | O85: 5 | P85: 929.57 | Q85: 91090 | R85: =ISNUMBER(MATCH(Q85,'Returned order'!A:A,0)) -> FALSE | S85: 42117
A86: 19058 | B86: Critical | C86: 0.09 | D86: 32.98 | E86: 151 | F86: Geoffrey Zhu | G86: Home Office | H86: Technology | I86: Computer Peripherals | J86: PC Concepts 116 Key Quantum 3000 Keyboard | K86: Wroclaw | L86: Thursday | M86: =VLOOKUP(L86,$U$2:$V$8,2,0) -> 4 | N86: -20.258 | O86: 2 | P86: 62.46 | Q86: 89521 | R86: =ISNUMBER(MATCH(Q86,'Returned order'!A:A,0)) -> FALSE | S86: 42026
... A123: 23605 | B123: Medium | C123: 0.01 | D123: 10.06 | E123: 211 | F123: Anna Wood | G123: Consumer | H123: Office Supplies | I123: Paper | J123: Riverleaf Stik-Withit® Designer Note Cubes® | K123: Lodz | L123: Tuesday | M123: =VLOOKUP(L123,$U$2:$V$8,2,0) -> 2 | N123: 7.59 | O123: 2 | P123: 21.2 | Q123: 85964 | R123: =ISNUMBER(MATCH(Q123,'Returned order'!A:A,0)) -> FALSE | S123: 42010
A124: 23606 | B124: Medium | C124: 0 | D124: 65.99 | E124: 211 | F124: Anna Wood | G124: Consumer | H124: Technology | I124: Telephones and Communication | J124: 252 | K124: Lodz | L124: Tuesday | M124: =VLOOKUP(L124,$U$2:$V$8,2,0) -> 2 | N124: -107.987 | O124: 3 | P124: 173.32 | Q124: 85964 | R124: =ISNUMBER(MATCH(Q124,'Returned order'!A:A,0)) -> FALSE | S124: 42010
A125: 23100 | B125: Medium | C125: 0.05 | D125: 2.08 | E125: 211 | F125: Anna Wood | G125: Home Office | H125: Office Supplies | I125: Scissors, Rulers and Trimmers | J125: Kleencut® Forged Office Shears by Acme United Corporation | K125: Lodz | L125: Tuesday | M125: =VLOOKUP(L125,$U$2:$V$8,2,0) -> 2 | N125: -36.25 | O125: 20 | P125: 42.29 | Q125: 85966 | R125: =ISNUMBER(MATCH(Q125,'Returned order'!A:A,0)) -> FALSE | S125: 42157
A126: 26303 | B126: Medium | C126: 0.05 | D126: 119.99 | E126: 218 | F126: Frances Saunders | G126: Consumer | H126: Technology | I126: Office Machines | J126: Hewlett-Packard 2600DN Business Color Inkjet Printer | K126: Warsaw | L126: Tuesday | M126: =VLOOKUP(L126,$U$2:$V$8,2,0) -> 2 | N126: -102.5121 | O126: 6 | P126: 730.37 | Q126: 88048 | R126: =ISNUMBER(MATCH(Q126,'Returned order'!A:A,0)) -> FALSE | S126: 42164
A127: 21203 | B127: Medium | C127: 0.03 | D127: 60.89 | E127: 228 | F127: Colleen Andrews | G127: Small Business | H127: Furniture | I127: Chairs & Chairmats | J127: Global Push Button Manager's Chair, Indigo | K127: Wroclaw | L127: Thursday | M127: =VLOOKUP(L127,$U$2:$V$8,2,0) -> 4 | N127: 36.354 | O127: 7 | P127: 450.49 | Q127: 88527 | R127: =ISNUMBER(MATCH(Q127,'Returned order'!A:A,0)) -> FALSE | S127: 42096
A128: 25500 | B128: Medium | C128: 0.07 | D128: 5.81 | E128: 233 | F128: Michele Bullard | G128: Small Business | H128: Office Supplies | I128: Binders and Binder Accessories | J128: Fellowes Black Plastic Comb Bindings | K128: Krakow | L128: Friday | M128: =VLOOKUP(L128,$U$2:$V$8,2,0) -> 5 | N128: -243.2365 | O128: 10 | P128: 58.8 | Q128: 90237 | R128: =ISNUMBER(MATCH(Q128,'Returned order'!A:A,0)) -> FALSE | S128: 42055
A129: 25501 | B129: Medium | C129: 0.04 | D129: 9.65 | E129: 233 | F129: Michele Bullard | G129: Small Business | H129: Furniture | I129: Office Furnishings | J129: Eldon Expressions™ Desk Accessory, Wood Pencil Holder, Oak | K129: Krakow | L129: Friday | M129: =VLOOKUP(L129,$U$2:$V$8,2,0) -> 5 | N129: -53.62 | O129: 12 | P129: 120.47 | Q129: 90237 | R129: =ISNUMBER(MATCH(Q129,'Returned order'!A:A,0)) -> FALSE | S129: 42055
A130: 23058 | B130: Critical | C130: 0.06 | D130: 279.81 | E130: 234 | F130: Don Cameron | G130: Small Business | H130: Office Supplies | I130: Appliances | J130: Sanyo 2.5 Cubic Foot Mid-Size Office Refrigerators | K130: Krakow | L130: Thursday | M130: =VLOOKUP(L130,$U$2:$V$8,2,0) -> 4 | N130: 1103.9724 | O130: 6 | P130: 1599.96 | Q130: 90236 | R130: =ISNUMBER(MATCH(Q130,'Returned order'!A:A,0)) -> FALSE | S130: 42040
A131: 25121 | B131: High | C131: 0.03 | D131: 28.53 | E131: 234 | F131: Don Cameron | G131: Small Business | H131: Office Supplies | I131: Binders and Binder Accessories | J131: Lock-Up Easel 'Spel-Binder' | K131: Krakow | L131: Friday | M131: =VLOOKUP(L131,$U$2:$V$8,2,0) -> 5 | N131: 136.3371 | O131: 7 | P131: 197.59 | Q131: 90238 | R131: =ISNUMBER(MATCH(Q131,'Returned order'!A:A,0)) -> FALSE | S131: 42090
A132: 25122 | B132: High | C132: 0.01 | D132: 15.28 | E132: 234 | F132: Don Cameron | G132: Small Business | H132: Technology | I132: Computer Peripherals | J132: Memorex 4.7GB DVD+R, 3/Pack | K132: Krakow | L132: Friday | M132: =VLOOKUP(L132,$U$2:$V$8,2,0) -> 5 | N132: -12.46 | O132: 2 | P132: 33.04 | Q132: 90238 | R132: =ISNUMBER(MATCH(Q132,'Returned order'!A:A,0)) -> FALSE | S132: 42090
A133: 22044 | B133: Low | C133: 0.06 | D133: 3.34 | E133: 234 | F133: Don Cameron | G133: Small Business | H133: Office Supplies | I133: Pens & Art Supplies | J133: Eldon Spacemaker® Box, Quick-Snap Lid, Clear | K133: Krakow | L133: Tuesday | M133: =VLOOKUP(L133,$U$2:$V$8,2,0) -> 2 | N133: -175.86 | O133: 8 | P133: 27.45 | Q133: 90239 | R133: =ISNUMBER(MATCH(Q133,'Returned order'!A:A,0)) -> FALSE | S133: 42122
A134: 18885 | B134: Not Specified | C134: 0 | D134: 442.14 | E134: 236 | F134: Shawn McIntyre | G134: Corporate | H134: Technology | I134: Office Machines | J134: Okidata ML390 Turbo Dot Matrix Printers | K134: Warsaw | L134: Sunday | M134: =VLOOKUP(L134,$U$2:$V$8,2,0) -> 7 | N134: 3294.8259 | O134: 10 | P134: 4775.11 | Q134: 86621 | R134: =ISNUMBER(MATCH(Q134,'Returned order'!A:A,0)) -> FALSE | S134: 42057
A135: 24327 | B135: Medium | C135: 0.1 | D135: 19.98 | E135: 240 | F135: Gilbert Scarborough | G135: Small Business | H135: Office Supplies | I135: Paper | J135: Xerox Blank Computer Paper | K135: Warsaw | L135: Monday | M135: =VLOOKUP(L135,$U$2:$V$8,2,0) -> 1 | N135: 35.09 | O135: 3 | P135: 57.41 | Q135: 90479 | R135: =ISNUMBER(MATCH(Q135,'Returned order'!A:A,0)) -> FALSE | S135: 42114
A136: 24328 | B136: Medium | C136: 0.06 | D136: 259.71 | E136: 241 | F136: Amy Ellis Holder | G136: Small Business | H136: Furniture | I136: Tables | J136: Bevis Round Bullnose 29" High Table Top | K136: Warsaw | L136: Monday | M136: =VLOOKUP(L136,$U$2:$V$8,2,0) -> 1 | N136: 785.63 | O136: 11 | P136: 2809.87 | Q136: 90479 | R136: =ISNUMBER(MATCH(Q136,'Returned order'!A:A,0)) -> FALSE | S136: 42114
... A139: 18849 | B139: Medium | C139: 0.02 | D139: 146.05 | E139: 247 | F139: Marshall Brandt Briggs | G139: Corporate | H139: Furniture | I139: Tables | J139: BPI Conference Tables | K139: Wroclaw | L139: Monday | M139: =VLOOKUP(L139,$U$2:$V$8,2,0) -> 1 | N139: -101.192 | O139: 5 | P139: 798.69 | Q139: 89139 | R139: =ISNUMBER(MATCH(Q139,'Returned order'!A:A,0)) -> FALSE | S139: 42058
A140: 18850 | B140: Medium | C140: 0.06 | D140: 65.99 | E140: 247 | F140: Marshall Brandt Briggs | G140: Corporate | H140: Technology | I140: Telephones and Communication | J140: 252 | K140: Wroclaw | L140: Monday | M140: =VLOOKUP(L140,$U$2:$V$8,2,0) -> 1 | N140: -3.332 | O140: 14 | P140: 792.11 | Q140: 89139 | R140: =ISNUMBER(MATCH(Q140,'Returned order'!A:A,0)) -> FALSE | S140: 42058
A141: 18842 | B141: Medium | C141: 0.09 | D141: 2.88 | E141: 247 | F141: Marshall Brandt Briggs | G141: Corporate | H141: Office Supplies | I141: Labels | J141: Avery 514 | K141: Wroclaw | L141: Saturday | M141: =VLOOKUP(L141,$U$2:$V$8,2,0) -> 6 | N141: -145.082 | O141: 10 | P141: 28.73 | Q141: 89140 | R141: =ISNUMBER(MATCH(Q141,'Returned order'!A:A,0)) -> FALSE | S141: 42084
A142: 18773 | B142: Critical | C142: 0.02 | D142: 2.58 | E142: 250 | F142: Brenda Nelson Blanchard | G142: Corporate | H142: Office Supplies | I142: Pens & Art Supplies | J142: DIXON Oriole® Pencils | K142: Krakow | L142: Thursday | M142: =VLOOKUP(L142,$U$2:$V$8,2,0) -> 4 | N142: 1.108 | O142: 39 | P142: 109.74 | Q142: 87214 | R142: =ISNUMBER(MATCH(Q142,'Returned order'!A:A,0)) -> FALSE | S142: 42152
A143: 18774 | B143: Critical | C143: 0.02 | D143: 65.99 | E143: 250 | F143: Brenda Nelson Blanchard | G143: Corporate | H143: Technology | I143: Telephones and Communication | J143: StarTAC Series | K143: Krakow | L143: Thursday | M143: =VLOOKUP(L143,$U$2:$V$8,2,0) -> 4 | N143: 1061.379 | O143: 27 | P143: 1543.55 | Q143: 87214 | R143: =ISNUMBER(MATCH(Q143,'Returned order'!A:A,0)) -> FALSE | S143: 42152
A144: 18801 | B144: Medium | C144: 0.1 | D144: 280.98 | E144: 254 | F144: Brett Hawkins | G144: Home Office | H144: Furniture | I144: Tables | J144: Global Adaptabilities™ Conference Tables | K144: Warsaw | L144: Wednesday | M144: =VLOOKUP(L144,$U$2:$V$8,2,0) -> 3 | N144: -53.745 | O144: 5 | P144: 1332.82 | Q144: 86268 | R144: =ISNUMBER(MATCH(Q144,'Returned order'!A:A,0)) -> FALSE | S144: 42165
A145: 20577 | B145: Critical | C145: 0.03 | D145: 8.34 | E145: 256 | F145: Irene Li | G145: Home Office | H145: Office Supplies | I145: Scissors, Rulers and Trimmers | J145: Acme® Elite Stainless Steel Scissors | K145: Lodz | L145: Saturday | M145: =VLOOKUP(L145,$U$2:$V$8,2,0) -> 6 | N145: 0.684 | O145: 4 | P145: 34.64 | Q145: 86267 | R145: =ISNUMBER(MATCH(Q145,'Returned order'!A:A,0)) -> FALSE | S145: 42035
A146: 24498 | B146: Medium | C146: 0.05 | D146: 17.48 | E146: 258 | F146: Allan Shields | G146: Consumer | H146: Technology | I146: Computer Peripherals | J146: Maxell Pro 80 Minute CD-R, 10/Pack | K146: Wroclaw | L146: Friday | M146: =VLOOKUP(L146,$U$2:$V$8,2,0) -> 5 | N146: -127.008 | O146: 3 | P146: 52.47 | Q146: 85858 | R146: =ISNUMBER(MATCH(Q146,'Returned order'!A:A,0)) -> FALSE | S146: 42006
A147: 18011 | B147: Low | C147: 0.09 | D147: 2.88 | E147: 259 | F147: Edward Pugh | G147: Consumer | H147: Office Supplies | I147: Pens & Art Supplies | J147: Newell 340 | K147: Warsaw | L147: Monday | M147: =VLOOKUP(L147,$U$2:$V$8,2,0) -> 1 | N147: 5.7532 | O147: 10 | P147: 26.38 | Q147: 85857 | R147: =ISNUMBER(MATCH(Q147,'Returned order'!A:A,0)) -> FALSE | S147: 42023
...

Sheet Returned order
A1: Order ID | B1: Status
A2: 65 | B2: Returned
A3: 612 | B3: Returned
A4: 614 | B4: Returned
A5: 678 | B5: Returned
A6: 710 | B6: Returned
A7: 740 | B7: Returned
A8: 775 | B8: Returned
A9: 833 | B9: Returned
A10: 902 | B10: Returned
A11: 3300 | B11: Returned
A12: 3456 | B12: Returned
A13: 3525 | B13: Returned
... A1635: 182906 | B1635: Returned

Sheet Pivot Tables
B2: COUNTUNIQUE of Order ID | C2: Weekday helper | D2: Order Weekday
C3: 1 | D3: 1.00 Total | E3: 2 | F3: 2.00 Total | G3: 3 | H3: 3.00 Total | I3: 4 | J3: 4.00 Total | K3: 5 | L3: 5.00 Total | M3: 6 | N3: 6.00 Total | O3: 7 | P3: 7.00 Total
B4: City | C4: Monday | E4: Tuesday | G4: Wednesday | I4: Thursday | K4: Friday | M4: Saturday | O4: Sunday
B5: Krakow | C5: 53 | D5: 53 | E5: 48 | F5: 48 | G5: 57 | H5: 57 | I5: 65 | J5: 65 | K5: 65 | L5: 65 | M5: 58 | N5: 58 | O5: 54 | P5: 54 | AG5: Order returned | AH5: COUNTUNIQUE of Order ID | AI5: COUNTUNIQUE of Order ID | AO5: X | AP5: Y | AQ5: Color | AR5: Value
B6: Lodz | C6: 58 | D6: 58 | E6: 45 | F6: 45 | G6: 47 | H6: 47 | I6: 39 | J6: 39 | K6: 39 | L6: 39 | M6: 56 | N6: 56 | O6: 39 | P6: 39 | AD6: =AA6 -> Paper | AE6: =AB6 -> 284 | AG6: FALSE | AH6: 1354 | AI6: 0.99194139 | AN6: =AK6 -> Krakow | AO6: 2.5 | AP6: 1.5 | AQ6: 1 | AR6: =AL6 -> 77365.473
B7: Warsaw | C7: 43 | D7: 43 | E7: 38 | F7: 38 | G7: 56 | H7: 56 | I7: 57 | J7: 57 | K7: 44 | L7: 44 | M7: 60 | N7: 60 | O7: 38 | P7: 38 | AD7: =AA7 -> Binders and Binder Accessories | AE7: =AB7 -> 200 | AG7: TRUE | AH7: 11 | AI7: 0.0080586081 | AN7: =AK7 -> Lodz | AO7: 1.5 | AP7: 4.8 | AQ7: 2 | AR7: =AL7 -> 85291.403
B8: Wroclaw | C8: 44 | D8: 44 | E8: 44 | F8: 44 | G8: 40 | H8: 40 | I8: 62 | J8: 62 | K8: 46 | L8: 46 | M8: 50 | N8: 50 | O8: 40 | P8: 40 | AD8: =AA8 -> Telephones and Communication | AE8: =AB8 -> 194 | AG8: Grand Total | AH8: 1365 | AI8: 1 | AN8: =AK8 -> Warsaw | AO8: 3 | AP8: 5.8 | AQ8: 3 | AR8: =AL8 -> 75844.79
AD9: =AA9 -> Office Furnishings | AE9: =AB9 -> 185 | AN9: =AK9 -> Wroclaw | AO9: -1.5 | AP9: 3 | AQ9: 4 | AR9: =AL9 -> -14424.054
AD10: =AA10 -> Computer Peripherals | AE10: =AB10 -> 174 | AO10: 10 | AP10: 10
AO11: -5
BB30: =SUM(AU:AU) -> 1924337.9

Sheet Detail1-Lodz-1.00-Monday
A1: Unit Price | B1: Customer ID | C1: Customer Name | D1: Customer Segment | E1: Product Category | F1: Product Sub-Category | G1: Product Name | H1: City | I1: Order Weekday | J1: Weekday helper | K1: Profit | L1: Quantity ordered new | M1: Sales | N1: Order ID | O1: Order returned | P1: Order Date
A2: 3.8 | B2: 56 | C2: Randall Montgomery | D2: Consumer | E2: Office Supplies | F2: Binders and Binder Accessories | G2: Durable Pressboard Binders | H2: Lodz | I2: Monday | J2: 1 | K2: 19.6282 | L2: 20 | M2: 73.55 | N2: 88075 | O2: FALSE | P2: 42114
A3: 1.76 | B3: 56 | C3: Randall Montgomery | D3: Consumer | E3: Office Supplies | F3: Pens & Art Supplies | G3: Newell 310 | H3: Lodz | I3: Monday | J3: 1 | K3: -1.6524 | L3: 17 | M3: 29.57 | N3: 88075 | O3: FALSE | P3: 42114
A4: 122.99 | B4: 68 | C4: Scott Bunn | D4: Corporate | E4: Furniture | F4: Chairs & Chairmats | G4: Global High-Back Leather Tilter, Burgundy | H4: Lodz | I4: Monday | J4: 1 | K4: -2426.55 | L4: 49 | M4: 5718.85 | N4: 55713 | O4: FALSE | P4: 42037
A5: 122.99 | B5: 70 | C5: Annette Boone | D5: Corporate | E5: Furniture | F5: Chairs & Chairmats | G5: Global High-Back Leather Tilter, Burgundy | H5: Lodz | I5: Monday | J5: 1 | K5: -2426.55 | L5: 12 | M5: 1400.53 | N5: 87947 | O5: FALSE | P5: 42037
A6: 8.09 | B6: 84 | C6: Helen Stein | D6: Consumer | E6: Furniture | F6: Office Furnishings | G6: 6" Cubicle Wall Clock, Black | H6: Lodz | I6: Monday | J6: 1 | K6: -144.56 | L6: 11 | M6: 90.98 | N6: 87364 | O6: FALSE | P6: 42037
A7: 896.99 | B7: 84 | C7: Helen Stein | D7: Corporate | E7: Office Supplies | F7: Binders and Binder Accessories | G7: GBC DocuBind TL300 Electric Binding System | H7: Lodz | I7: Monday | J7: 1 | K7: 7402.32 | L7: 13 | M7: 10728 | N7: 87366 | O7: FALSE | P7: 42093
A8: 19.98 | B8: 101 | C8: Claudia Boyle | D8: Consumer | E8: Technology | F8: Computer Peripherals | G8: Belkin 105-Key Black Keyboard | H8: Lodz | I8: Monday | J8: 1 | K8: -16.2 | L8: 16 | M8: 303.59 | N8: 88205 | O8: FALSE | P8: 42177
A9: 300.98 | B9: 102 | C9: Caroline Johnston | D9: Consumer | E9: Furniture | F9: Bookcases | G9: Atlantic Metals Mobile 5-Shelf Bookcases, Custom Colors | H9: Lodz | I9: Monday | J9: 1 | K9: 2023.75 | L9: 31 | M9: 9459.94 | N9: 42599 | O9: FALSE | P9: 42100
A10: 19.98 | B10: 102 | C10: Caroline Johnston | D10: Consumer | E10: Technology | F10: Computer Peripherals | G10: Belkin 105-Key Black Keyboard | H10: Lodz | I10: Monday | J10: 1 | K10: -20.25 | L10: 65 | M10: 1233.32 | N10: 3397 | O10: FALSE | P10: 42177
A11: 2.88 | B11: 102 | C11: Caroline Johnston | D11: Consumer | E11: Office Supplies | F11: Binders and Binder Accessories | G11: Avery Durable Binders | H11: Lodz | I11: Monday | J11: 1 | K11: -3.381 | L11: 17 | M11: 47.31 | N11: 3397 | O11: FALSE | P11: 42177
A12: 300.98 | B12: 107 | C12: Lois Hamilton | D12: Consumer | E12: Furniture | F12: Bookcases | G12: Atlantic Metals Mobile 5-Shelf Bookcases, Custom Colors | H12: Lodz | I12: Monday | J12: 1 | K12: 1684.4763 | L12: 8 | M12: 2441.27 | N12: 88204 | O12: FALSE | P12: 42100
A13: 2.88 | B13: 109 | C13: Tom McFarland | D13: Consumer | E13: Office Supplies | F13: Binders and Binder Accessories | G13: Avery Durable Binders | H13: Lodz | I13: Monday | J13: 1 | K13: -2.7048 | L13: 4 | M13: 11.13 | N13: 88205 | O13: FALSE | P13: 42177
... A85: 3.57 | B85: 3374 | C85: Jamie Ward | D85: Home Office | E85: Office Supplies | F85: Pens & Art Supplies | G85: Barrel Sharpener | H85: Lodz | I85: Monday | J85: 1 | K85: -56.888 | L85: 9 | M85: 31.45 | N85: 87474 | O85: FALSE | P85: 42184

Sheet Dashboard
F9: =AE19 -> Monday | G9: =AF19 | H9: =AH19 | I9: =AJ19 | J9: =AL19 | K9: =AN19 | L9: =AP19
E10: =AD20 -> Krakow | F10: =AE20 -> 53 | G10: =AF20 -> 53 | H10: =AH20 -> 48 | I10: =AJ20 -> 57 | J10: =AK20 -> 65 | K10: =AN20 -> 65 | L10: =AP20 -> 58
E11: =AD21 -> Lodz | F11: =AE21 -> 58 | G11: 45 | H11: 47 | I11: 39 | J11: 39 | K11: 56 | L11: 39
E12: =AD22 -> Warsaw | F12: =AE22 -> 43 | G12: 38 | H12: 56 | I12: 57 | J12: 44 | K12: 60 | L12: 38
E13: =AD23 -> Wroclaw | F13: =AE23 -> 44 | G13: 44 | H13: 40 | I13: 62 | J13: 46 | K13: 50 | L13: 40
AD17: COUNTUNIQUE of Order ID | AE17: Weekday helper | AF17: Order Weekday
Z18: =SUM(BW:BW) -> 224077.61 | AE18: 1 | AF18: 1.00 Total | AG18: 2 | AH18: 2.00 Total | AI18: 3 | AJ18: 3.00 Total | AK18: 4 | AL18: 4.00 Total | AM18: 5 | AN18: 5.00 Total | AO18: 6 | AP18: 6.00 Total | AQ18: 7 | AR18: 7.00 Total
AD19: City | AE19: Monday | AG19: Tuesday | AI19: Wednesday | AK19: Thursday | AM19: Friday | AO19: Saturday | AQ19: Sunday
AD20: Krakow | AE20: 53 | AF20: 53 | AG20: 48 | AH20: 48 | AI20: 57 | AJ20: 57 | AK20: 65 | AL20: 65 | AM20: 65 | AN20: 65 | AO20: 58 | AP20: 58 | AQ20: 54 | AR20: 54 | BH20: Order returned | BI20: COUNTUNIQUE of Order ID | BJ20: COUNTUNIQUE of Order ID | BP20: X | BQ20: Y | BR20: Color | BS20: Value
AD21: Lodz | AE21: 58 | AF21: 58 | AG21: 45 | AH21: 45 | AI21: 47 | AJ21: 47 | AK21: 39 | AL21: 39 | AM21: 39 | AN21: 39 | AO21: 56 | AP21: 56 | AQ21: 39 | AR21: 39 | BE21: =BB21 -> Paper | BF21: =BC21 -> 284 | BH21: FALSE | BI21: 1354 | BJ21: 0.99194139 | BO21: =BL21 -> Krakow | BP21: 2.5 | BQ21: 1.5 | BR21: 1 | BS21: =BM21 -> 77365.473
AD22: Warsaw | AE22: 43 | AF22: 43 | AG22: 38 | AH22: 38 | AI22: 56 | AJ22: 56 | AK22: 57 | AL22: 57 | AM22: 44 | AN22: 44 | AO22: 60 | AP22: 60 | AQ22: 38 | AR22: 38 | BE22: =BB22 -> Binders and Binder Accessories | BF22: =BC22 -> 200 | BH22: TRUE | BI22: 11 | BJ22: 0.0080586081 | BO22: =BL22 -> Lodz | BP22: 1.5 | BQ22: 4.8 | BR22: 2 | BS22: =BM22 -> 85291.403
AD23: Wroclaw | AE23: 44 | AF23: 44 | AG23: 44 | AH23: 44 | AI23: 40 | AJ23: 40 | AK23: 62 | AL23: 62 | AM23: 46 | AN23: 46 | AO23: 50 | AP23: 50 | AQ23: 40 | AR23: 40 | BE23: =BB23 -> Telephones and Communication | BF23: =BC23 -> 194 | BH23: Grand Total | BI23: 1365 | BJ23: 1 | BO23: =BL23 -> Warsaw | BP23: 3 | BQ23: 5.8 | BR23: 3 | BS23: =BM23 -> 75844.79
BE24: =BB24 -> Office Furnishings | BF24: =BC24 -> 185 | BO24: =BL24 -> Wroclaw | BP24: -1.5 | BQ24: 3 | BR24: 4 | BS24: =BM24 -> -14424.054
BE25: =BB25 -> Computer Peripherals | BF25: =BC25 -> 174 | BP25: 10 | BQ25: 10
Z26: =SUM(BV:BV) -> 1924337.9 | BP26: -5
O36: =BO21 -> Krakow | P36: =BS21 -> 77365.473
O37: =BO22 -> Lodz | P37: =BS22 -> 85291.403
O38: =BO23 -> Warsaw | P38: =BS23 -> 75844.79
O39: =BO24 -> Wroclaw | P39: =BS24 -> -14424.054
E50: =BI23 -> 1365 | H50: =BI22 -> 11 | K50: =BJ22 -> 0.0080586081
